{"box_data": [{"position": {"minX": 370.75, "minY": 191.25, "maxX": 443.75, "maxY": 319.25}, "class_id": 2, "box_caption": "ElectricBox 0.861", "scores": {"class_score": 0.86083984375}, "domain": "pixel"}, {"position": {"minX": 50.78125, "minY": 189.5, "maxX": 123.5, "maxY": 314.75}, "class_id": 2, "box_caption": "ElectricBox 0.833", "scores": {"class_score": 0.83349609375}, "domain": "pixel"}, {"position": {"minX": 132.25, "minY": 291.25, "maxX": 149.75, "maxY": 330.25}, "class_id": 3, "box_caption": "FireExtinguisher 0.724", "scores": {"class_score": 0.7236328125}, "domain": "pixel"}, {"position": {"minX": 451.25, "minY": 295.0, "maxX": 467.75, "maxY": 333.0}, "class_id": 3, "box_caption": "FireExtinguisher 0.681", "scores": {"class_score": 0.68115234375}, "domain": "pixel"}, {"position": {"minX": 70.25, "minY": 216.5, "maxX": 80.75, "maxY": 243.5}, "class_id": 8, "box_caption": "Worning 0.609", "scores": {"class_score": 0.609375}, "domain": "pixel"}, {"position": {"minX": 391.0, "minY": 219.875, "maxX": 401.0, "maxY": 244.875}, "class_id": 8, "box_caption": "Worning 0.448", "scores": {"class_score": 0.447998046875}, "domain": "pixel"}, {"position": {"minX": 250.875, "minY": 252.25, "maxX": 269.75, "maxY": 282.75}, "class_id": 8, "box_caption": "Worning 0.338", "scores": {"class_score": 0.337646484375}, "domain": "pixel"}, {"position": {"minX": 646.0, "minY": 353.0, "maxX": 660.0, "maxY": 381.0}, "class_id": 8, "box_caption": "Worning 0.200", "scores": {"class_score": 0.1995849609375}, "domain": "pixel"}, {"position": {"minX": 63.5, "minY": 211.75, "maxX": 88.625, "maxY": 267.25}, "class_id": 8, "box_caption": "Worning 0.172", "scores": {"class_score": 0.171630859375}, "domain": "pixel"}, {"position": {"minX": 63.5, "minY": 211.75, "maxX": 88.625, "maxY": 267.25}, "class_id": 2, "box_caption": "ElectricBox 0.143", "scores": {"class_score": 0.14306640625}, "domain": "pixel"}, {"position": {"minX": 383.25, "minY": 215.875, "maxX": 409.75, "maxY": 267.0}, "class_id": 8, "box_caption": "Worning 0.089", "scores": {"class_score": 0.0888671875}, "domain": "pixel"}, {"position": {"minX": 389.25, "minY": 221.0, "maxX": 404.25, "maxY": 251.25}, "class_id": 8, "box_caption": "Worning 0.083", "scores": {"class_score": 0.08331298828125}, "domain": "pixel"}, {"position": {"minX": 66.0, "minY": 214.75, "maxX": 82.75, "maxY": 244.0}, "class_id": 8, "box_caption": "Worning 0.072", "scores": {"class_score": 0.0716552734375}, "domain": "pixel"}, {"position": {"minX": 383.25, "minY": 215.875, "maxX": 409.75, "maxY": 267.0}, "class_id": 2, "box_caption": "ElectricBox 0.042", "scores": {"class_score": 0.04248046875}, "domain": "pixel"}, {"position": {"minX": 446.5, "minY": 294.75, "maxX": 463.5, "maxY": 334.75}, "class_id": 3, "box_caption": "FireExtinguisher 0.036", "scores": {"class_score": 0.036163330078125}, "domain": "pixel"}, {"position": {"minX": 372.25, "minY": 197.375, "maxX": 435.25, "maxY": 302.0}, "class_id": 8, "box_caption": "Worning 0.017", "scores": {"class_score": 0.017333984375}, "domain": "pixel"}, {"position": {"minX": 648.5, "minY": 349.5, "maxX": 663.5, "maxY": 390.0}, "class_id": 8, "box_caption": "Worning 0.015", "scores": {"class_score": 0.01464080810546875}, "domain": "pixel"}, {"position": {"minX": 52.40625, "minY": 188.875, "maxX": 117.5, "maxY": 305.25}, "class_id": 8, "box_caption": "Worning 0.014", "scores": {"class_score": 0.01433563232421875}, "domain": "pixel"}, {"position": {"minX": 566.5, "minY": 254.0, "maxX": 588.5, "maxY": 289.0}, "class_id": 2, "box_caption": "ElectricBox 0.012", "scores": {"class_score": 0.01180267333984375}, "domain": "pixel"}, {"position": {"minX": 563.5, "minY": 253.75, "maxX": 585.5, "maxY": 287.25}, "class_id": 8, "box_caption": "Worning 0.011", "scores": {"class_score": 0.0111083984375}, "domain": "pixel"}, {"position": {"minX": 532.0, "minY": 380.75, "maxX": 685.0, "maxY": 528.0}, "class_id": 2, "box_caption": "ElectricBox 0.009", "scores": {"class_score": 0.00905609130859375}, "domain": "pixel"}, {"position": {"minX": 381.0, "minY": 203.75, "maxX": 412.5, "maxY": 276.25}, "class_id": 8, "box_caption": "Worning 0.009", "scores": {"class_score": 0.0087432861328125}, "domain": "pixel"}, {"position": {"minX": 385.0, "minY": 212.5, "maxX": 401.0, "maxY": 247.0}, "class_id": 8, "box_caption": "Worning 0.009", "scores": {"class_score": 0.00860595703125}, "domain": "pixel"}, {"position": {"minX": 249.875, "minY": 252.125, "maxX": 269.75, "maxY": 282.75}, "class_id": 2, "box_caption": "ElectricBox 0.008", "scores": {"class_score": 0.00849151611328125}, "domain": "pixel"}, {"position": {"minX": 61.5, "minY": 209.875, "maxX": 74.5, "maxY": 244.125}, "class_id": 8, "box_caption": "Worning 0.008", "scores": {"class_score": 0.0078125}, "domain": "pixel"}, {"position": {"minX": 381.25, "minY": 210.375, "maxX": 416.25, "maxY": 275.25}, "class_id": 2, "box_caption": "ElectricBox 0.008", "scores": {"class_score": 0.00772857666015625}, "domain": "pixel"}, {"position": {"minX": 125.75, "minY": 291.75, "maxX": 144.25, "maxY": 330.75}, "class_id": 3, "box_caption": "FireExtinguisher 0.008", "scores": {"class_score": 0.007640838623046875}, "domain": "pixel"}, {"position": {"minX": 69.25, "minY": 217.125, "maxX": 82.0, "maxY": 246.125}, "class_id": 2, "box_caption": "ElectricBox 0.007", "scores": {"class_score": 0.006618499755859375}, "domain": "pixel"}, {"position": {"minX": 245.375, "minY": 248.75, "maxX": 268.75, "maxY": 287.75}, "class_id": 8, "box_caption": "Worning 0.006", "scores": {"class_score": 0.006195068359375}, "domain": "pixel"}, {"position": {"minX": 387.75, "minY": 212.875, "maxX": 405.75, "maxY": 257.75}, "class_id": 8, "box_caption": "Worning 0.006", "scores": {"class_score": 0.006038665771484375}, "domain": "pixel"}, {"position": {"minX": 67.3125, "minY": 205.5, "maxX": 89.3125, "maxY": 248.5}, "class_id": 8, "box_caption": "Worning 0.006", "scores": {"class_score": 0.00579071044921875}, "domain": "pixel"}, {"position": {"minX": 131.875, "minY": 289.25, "maxX": 150.625, "maxY": 330.75}, "class_id": 2, "box_caption": "ElectricBox 0.006", "scores": {"class_score": 0.0057525634765625}, "domain": "pixel"}, {"position": {"minX": 279.25, "minY": 124.9375, "maxX": 305.75, "maxY": 148.875}, "class_id": 8, "box_caption": "Worning 0.005", "scores": {"class_score": 0.005413055419921875}, "domain": "pixel"}, {"position": {"minX": 357.25, "minY": 204.875, "maxX": 428.25, "maxY": 318.25}, "class_id": 2, "box_caption": "ElectricBox 0.004", "scores": {"class_score": 0.0042877197265625}, "domain": "pixel"}, {"position": {"minX": 378.75, "minY": 216.25, "maxX": 390.75, "maxY": 242.75}, "class_id": 8, "box_caption": "Worning 0.004", "scores": {"class_score": 0.00421905517578125}, "domain": "pixel"}, {"position": {"minX": 609.0, "minY": 7.625, "maxX": 671.0, "maxY": 193.625}, "class_id": 2, "box_caption": "ElectricBox 0.004", "scores": {"class_score": 0.00408935546875}, "domain": "pixel"}, {"position": {"minX": 133.625, "minY": 290.75, "maxX": 149.875, "maxY": 332.25}, "class_id": 0, "box_caption": "Chemicals 0.004", "scores": {"class_score": 0.003948211669921875}, "domain": "pixel"}, {"position": {"minX": 535.0, "minY": -20.4375, "maxX": 685.0, "maxY": 172.5}, "class_id": 2, "box_caption": "ElectricBox 0.004", "scores": {"class_score": 0.00394439697265625}, "domain": "pixel"}, {"position": {"minX": 645.5, "minY": 343.5, "maxX": 661.5, "maxY": 385.0}, "class_id": 8, "box_caption": "Worning 0.004", "scores": {"class_score": 0.0038299560546875}, "domain": "pixel"}, {"position": {"minX": 131.375, "minY": 290.25, "maxX": 150.375, "maxY": 331.75}, "class_id": 9, "box_caption": "people 0.003", "scores": {"class_score": 0.0034027099609375}, "domain": "pixel"}, {"position": {"minX": 375.75, "minY": 217.5, "maxX": 384.75, "maxY": 236.75}, "class_id": 8, "box_caption": "Worning 0.003", "scores": {"class_score": 0.003204345703125}, "domain": "pixel"}, {"position": {"minX": 436.5, "minY": 296.75, "maxX": 470.0, "maxY": 338.25}, "class_id": 3, "box_caption": "FireExtinguisher 0.003", "scores": {"class_score": 0.0031757354736328125}, "domain": "pixel"}, {"position": {"minX": 119.0, "minY": 294.25, "maxX": 151.25, "maxY": 333.75}, "class_id": 3, "box_caption": "FireExtinguisher 0.003", "scores": {"class_score": 0.0031566619873046875}, "domain": "pixel"}, {"position": {"minX": 370.75, "minY": 212.625, "maxX": 378.25, "maxY": 230.625}, "class_id": 8, "box_caption": "Worning 0.003", "scores": {"class_score": 0.0030498504638671875}, "domain": "pixel"}, {"position": {"minX": 450.75, "minY": 294.5, "maxX": 468.25, "maxY": 335.0}, "class_id": 2, "box_caption": "ElectricBox 0.003", "scores": {"class_score": 0.00299835205078125}, "domain": "pixel"}, {"position": {"minX": 450.5, "minY": 293.75, "maxX": 468.0, "maxY": 334.75}, "class_id": 7, "box_caption": "Valve 0.003", "scores": {"class_score": 0.002986907958984375}, "domain": "pixel"}, {"position": {"minX": 568.0, "minY": 404.0, "maxX": 680.0, "maxY": 522.5}, "class_id": 2, "box_caption": "ElectricBox 0.003", "scores": {"class_score": 0.0029277801513671875}, "domain": "pixel"}, {"position": {"minX": 607.0, "minY": 390.0, "maxX": 676.0, "maxY": 520.0}, "class_id": 2, "box_caption": "ElectricBox 0.003", "scores": {"class_score": 0.0028247833251953125}, "domain": "pixel"}, {"position": {"minX": 131.75, "minY": 289.5, "maxX": 150.25, "maxY": 331.0}, "class_id": 6, "box_caption": "Tank 0.003", "scores": {"class_score": 0.002819061279296875}, "domain": "pixel"}, {"position": {"minX": 389.25, "minY": 221.0, "maxX": 404.25, "maxY": 251.25}, "class_id": 2, "box_caption": "ElectricBox 0.003", "scores": {"class_score": 0.0026702880859375}, "domain": "pixel"}, {"position": {"minX": 371.0, "minY": 192.75, "maxX": 442.5, "maxY": 319.75}, "class_id": 3, "box_caption": "FireExtinguisher 0.002", "scores": {"class_score": 0.0024585723876953125}, "domain": "pixel"}, {"position": {"minX": 451.5, "minY": 294.0, "maxX": 468.0, "maxY": 334.5}, "class_id": 0, "box_caption": "Chemicals 0.002", "scores": {"class_score": 0.002445220947265625}, "domain": "pixel"}, {"position": {"minX": 452.5, "minY": 295.75, "maxX": 468.5, "maxY": 333.75}, "class_id": 11, "box_caption": "people1 0.002", "scores": {"class_score": 0.002437591552734375}, "domain": "pixel"}, {"position": {"minX": 55.0625, "minY": 209.75, "maxX": 65.0625, "maxY": 232.0}, "class_id": 8, "box_caption": "Worning 0.002", "scores": {"class_score": 0.0024242401123046875}, "domain": "pixel"}, {"position": {"minX": 52.15625, "minY": 190.75, "maxX": 121.0, "maxY": 316.25}, "class_id": 3, "box_caption": "FireExtinguisher 0.002", "scores": {"class_score": 0.0023517608642578125}, "domain": "pixel"}, {"position": {"minX": 131.75, "minY": 289.25, "maxX": 150.25, "maxY": 331.75}, "class_id": 8, "box_caption": "Worning 0.002", "scores": {"class_score": 0.0023479461669921875}, "domain": "pixel"}, {"position": {"minX": 131.375, "minY": 290.25, "maxX": 150.375, "maxY": 331.75}, "class_id": 7, "box_caption": "Valve 0.002", "scores": {"class_score": 0.0023345947265625}, "domain": "pixel"}, {"position": {"minX": 374.75, "minY": 213.5, "maxX": 383.75, "maxY": 233.5}, "class_id": 8, "box_caption": "Worning 0.002", "scores": {"class_score": 0.0023174285888671875}, "domain": "pixel"}, {"position": {"minX": 371.0, "minY": 192.75, "maxX": 442.5, "maxY": 319.75}, "class_id": 11, "box_caption": "people1 0.002", "scores": {"class_score": 0.002170562744140625}, "domain": "pixel"}, {"position": {"minX": 450.5, "minY": 293.5, "maxX": 468.0, "maxY": 333.5}, "class_id": 6, "box_caption": "Tank 0.002", "scores": {"class_score": 0.0021533966064453125}, "domain": "pixel"}, {"position": {"minX": 371.0, "minY": 192.75, "maxX": 442.5, "maxY": 319.75}, "class_id": 0, "box_caption": "Chemicals 0.002", "scores": {"class_score": 0.0021381378173828125}, "domain": "pixel"}, {"position": {"minX": 52.15625, "minY": 190.75, "maxX": 121.0, "maxY": 316.25}, "class_id": 9, "box_caption": "people 0.002", "scores": {"class_score": 0.0021343231201171875}, "domain": "pixel"}, {"position": {"minX": 371.0, "minY": 192.75, "maxX": 442.5, "maxY": 319.75}, "class_id": 9, "box_caption": "people 0.002", "scores": {"class_score": 0.0021209716796875}, "domain": "pixel"}, {"position": {"minX": 134.0, "minY": 291.75, "maxX": 149.75, "maxY": 331.25}, "class_id": 11, "box_caption": "people1 0.002", "scores": {"class_score": 0.0021152496337890625}, "domain": "pixel"}, {"position": {"minX": 70.25, "minY": 216.5, "maxX": 80.75, "maxY": 243.5}, "class_id": 3, "box_caption": "FireExtinguisher 0.002", "scores": {"class_score": 0.0020294189453125}, "domain": "pixel"}, {"position": {"minX": 502.25, "minY": 20.375, "maxX": 675.5, "maxY": 183.125}, "class_id": 2, "box_caption": "ElectricBox 0.002", "scores": {"class_score": 0.0020084381103515625}, "domain": "pixel"}, {"position": {"minX": 52.15625, "minY": 190.75, "maxX": 121.0, "maxY": 316.25}, "class_id": 0, "box_caption": "Chemicals 0.002", "scores": {"class_score": 0.0019969940185546875}, "domain": "pixel"}, {"position": {"minX": 450.5, "minY": 293.75, "maxX": 468.0, "maxY": 334.75}, "class_id": 9, "box_caption": "people 0.002", "scores": {"class_score": 0.001995086669921875}, "domain": "pixel"}, {"position": {"minX": 52.15625, "minY": 190.75, "maxX": 121.0, "maxY": 316.25}, "class_id": 11, "box_caption": "people1 0.002", "scores": {"class_score": 0.001983642578125}, "domain": "pixel"}, {"position": {"minX": 371.0, "minY": 192.75, "maxX": 442.5, "maxY": 319.75}, "class_id": 7, "box_caption": "Valve 0.002", "scores": {"class_score": 0.00197601318359375}, "domain": "pixel"}, {"position": {"minX": 52.0, "minY": 186.5, "maxX": 123.0, "maxY": 319.0}, "class_id": 6, "box_caption": "Tank 0.002", "scores": {"class_score": 0.00183868408203125}, "domain": "pixel"}, {"position": {"minX": 52.15625, "minY": 190.75, "maxX": 121.0, "maxY": 316.25}, "class_id": 7, "box_caption": "Valve 0.002", "scores": {"class_score": 0.0018339157104492188}, "domain": "pixel"}, {"position": {"minX": 371.0, "minY": 192.75, "maxX": 442.5, "maxY": 319.75}, "class_id": 5, "box_caption": "Ladder 0.002", "scores": {"class_score": 0.0018215179443359375}, "domain": "pixel"}, {"position": {"minX": 132.25, "minY": 289.5, "maxX": 150.25, "maxY": 332.0}, "class_id": 1, "box_caption": "Cones 0.002", "scores": {"class_score": 0.0017490386962890625}, "domain": "pixel"}, {"position": {"minX": 250.875, "minY": 252.25, "maxX": 269.75, "maxY": 282.75}, "class_id": 0, "box_caption": "Chemicals 0.002", "scores": {"class_score": 0.0017480850219726562}, "domain": "pixel"}, {"position": {"minX": 371.0, "minY": 192.75, "maxX": 442.5, "maxY": 319.75}, "class_id": 6, "box_caption": "Tank 0.002", "scores": {"class_score": 0.0017242431640625}, "domain": "pixel"}, {"position": {"minX": 131.75, "minY": 289.25, "maxX": 150.25, "maxY": 331.75}, "class_id": 5, "box_caption": "Ladder 0.002", "scores": {"class_score": 0.0016927719116210938}, "domain": "pixel"}, {"position": {"minX": 52.15625, "minY": 190.75, "maxX": 121.0, "maxY": 316.25}, "class_id": 5, "box_caption": "Ladder 0.002", "scores": {"class_score": 0.00167083740234375}, "domain": "pixel"}, {"position": {"minX": 36.3125, "minY": 209.5, "maxX": 95.8125, "maxY": 310.0}, "class_id": 2, "box_caption": "ElectricBox 0.002", "scores": {"class_score": 0.0016698837280273438}, "domain": "pixel"}, {"position": {"minX": 65.4375, "minY": 209.75, "maxX": 83.0625, "maxY": 248.0}, "class_id": 2, "box_caption": "ElectricBox 0.002", "scores": {"class_score": 0.0016651153564453125}, "domain": "pixel"}, {"position": {"minX": 643.5, "minY": 357.75, "maxX": 657.5, "maxY": 380.75}, "class_id": 8, "box_caption": "Worning 0.002", "scores": {"class_score": 0.0016050338745117188}, "domain": "pixel"}, {"position": {"minX": 207.625, "minY": 238.625, "maxX": 274.5, "maxY": 343.0}, "class_id": 2, "box_caption": "ElectricBox 0.002", "scores": {"class_score": 0.0016040802001953125}, "domain": "pixel"}, {"position": {"minX": 451.75, "minY": 295.25, "maxX": 468.25, "maxY": 334.75}, "class_id": 10, "box_caption": "people0 0.002", "scores": {"class_score": 0.0015649795532226562}, "domain": "pixel"}, {"position": {"minX": 451.75, "minY": 295.25, "maxX": 468.25, "maxY": 334.75}, "class_id": 1, "box_caption": "Cones 0.002", "scores": {"class_score": 0.0015516281127929688}, "domain": "pixel"}, {"position": {"minX": 355.5, "minY": 326.5, "maxX": 718.5, "maxY": 562.0}, "class_id": 2, "box_caption": "ElectricBox 0.002", "scores": {"class_score": 0.0015363693237304688}, "domain": "pixel"}, {"position": {"minX": 451.25, "minY": 295.0, "maxX": 467.75, "maxY": 333.0}, "class_id": 8, "box_caption": "Worning 0.002", "scores": {"class_score": 0.0015316009521484375}, "domain": "pixel"}, {"position": {"minX": 66.9375, "minY": 212.125, "maxX": 78.5625, "maxY": 239.125}, "class_id": 8, "box_caption": "Worning 0.002", "scores": {"class_score": 0.0015268325805664062}, "domain": "pixel"}, {"position": {"minX": 371.0, "minY": 192.75, "maxX": 442.5, "maxY": 319.75}, "class_id": 4, "box_caption": "Hole 0.002", "scores": {"class_score": 0.0015048980712890625}, "domain": "pixel"}, {"position": {"minX": 121.875, "minY": 293.0, "maxX": 137.125, "maxY": 327.5}, "class_id": 3, "box_caption": "FireExtinguisher 0.001", "scores": {"class_score": 0.0014905929565429688}, "domain": "pixel"}, {"position": {"minX": 571.0, "minY": 7.875, "maxX": 673.0, "maxY": 186.875}, "class_id": 2, "box_caption": "ElectricBox 0.001", "scores": {"class_score": 0.00148773193359375}, "domain": "pixel"}, {"position": {"minX": 52.15625, "minY": 190.75, "maxX": 121.0, "maxY": 316.25}, "class_id": 4, "box_caption": "Hole 0.001", "scores": {"class_score": 0.0014410018920898438}, "domain": "pixel"}, {"position": {"minX": 371.0, "minY": 192.75, "maxX": 442.5, "maxY": 319.75}, "class_id": 10, "box_caption": "people0 0.001", "scores": {"class_score": 0.0014362335205078125}, "domain": "pixel"}, {"position": {"minX": 52.0, "minY": 186.5, "maxX": 123.0, "maxY": 319.0}, "class_id": 12, "box_caption": "stairs 0.001", "scores": {"class_score": 0.0014324188232421875}, "domain": "pixel"}, {"position": {"minX": 442.0, "minY": 297.0, "maxX": 458.5, "maxY": 333.0}, "class_id": 3, "box_caption": "FireExtinguisher 0.001", "scores": {"class_score": 0.0014171600341796875}, "domain": "pixel"}, {"position": {"minX": 450.75, "minY": 294.5, "maxX": 468.25, "maxY": 335.0}, "class_id": 5, "box_caption": "Ladder 0.001", "scores": {"class_score": 0.0014171600341796875}, "domain": "pixel"}, {"position": {"minX": 451.25, "minY": 295.0, "maxX": 467.75, "maxY": 333.0}, "class_id": 12, "box_caption": "stairs 0.001", "scores": {"class_score": 0.0014162063598632812}, "domain": "pixel"}, {"position": {"minX": 250.875, "minY": 252.25, "maxX": 269.75, "maxY": 282.75}, "class_id": 6, "box_caption": "Tank 0.001", "scores": {"class_score": 0.0014123916625976562}, "domain": "pixel"}, {"position": {"minX": 371.0, "minY": 192.75, "maxX": 442.5, "maxY": 319.75}, "class_id": 1, "box_caption": "Cones 0.001", "scores": {"class_score": 0.0014085769653320312}, "domain": "pixel"}, {"position": {"minX": 70.25, "minY": 216.5, "maxX": 80.75, "maxY": 243.5}, "class_id": 12, "box_caption": "stairs 0.001", "scores": {"class_score": 0.0013751983642578125}, "domain": "pixel"}, {"position": {"minX": 63.5, "minY": 211.75, "maxX": 88.625, "maxY": 267.25}, "class_id": 7, "box_caption": "Valve 0.001", "scores": {"class_score": 0.001369476318359375}, "domain": "pixel"}, {"position": {"minX": 390.75, "minY": 219.25, "maxX": 401.25, "maxY": 245.5}, "class_id": 3, "box_caption": "FireExtinguisher 0.001", "scores": {"class_score": 0.0013580322265625}, "domain": "pixel"}, {"position": {"minX": 132.25, "minY": 289.5, "maxX": 150.25, "maxY": 332.0}, "class_id": 10, "box_caption": "people0 0.001", "scores": {"class_score": 0.0013580322265625}, "domain": "pixel"}, {"position": {"minX": 455.5, "minY": 370.25, "maxX": 684.5, "maxY": 520.0}, "class_id": 2, "box_caption": "ElectricBox 0.001", "scores": {"class_score": 0.0013561248779296875}, "domain": "pixel"}, {"position": {"minX": -0.54296875, "minY": 223.625, "maxX": 9.8125, "maxY": 291.25}, "class_id": 2, "box_caption": "ElectricBox 0.001", "scores": {"class_score": 0.001354217529296875}, "domain": "pixel"}, {"position": {"minX": 70.25, "minY": 216.5, "maxX": 80.75, "maxY": 243.5}, "class_id": 9, "box_caption": "people 0.001", "scores": {"class_score": 0.0013523101806640625}, "domain": "pixel"}, {"position": {"minX": 52.15625, "minY": 190.75, "maxX": 121.0, "maxY": 316.25}, "class_id": 1, "box_caption": "Cones 0.001", "scores": {"class_score": 0.0013418197631835938}, "domain": "pixel"}, {"position": {"minX": 52.15625, "minY": 190.75, "maxX": 121.0, "maxY": 316.25}, "class_id": 10, "box_caption": "people0 0.001", "scores": {"class_score": 0.0013265609741210938}, "domain": "pixel"}, {"position": {"minX": 69.25, "minY": 217.125, "maxX": 82.0, "maxY": 246.125}, "class_id": 5, "box_caption": "Ladder 0.001", "scores": {"class_score": 0.0013113021850585938}, "domain": "pixel"}, {"position": {"minX": 63.5, "minY": 211.75, "maxX": 88.625, "maxY": 267.25}, "class_id": 5, "box_caption": "Ladder 0.001", "scores": {"class_score": 0.001285552978515625}, "domain": "pixel"}, {"position": {"minX": 129.5, "minY": 283.25, "maxX": 146.0, "maxY": 328.75}, "class_id": 3, "box_caption": "FireExtinguisher 0.001", "scores": {"class_score": 0.001239776611328125}, "domain": "pixel"}, {"position": {"minX": 134.0, "minY": 291.75, "maxX": 149.75, "maxY": 331.25}, "class_id": 12, "box_caption": "stairs 0.001", "scores": {"class_score": 0.0012073516845703125}, "domain": "pixel"}, {"position": {"minX": 132.25, "minY": 289.5, "maxX": 150.25, "maxY": 332.0}, "class_id": 4, "box_caption": "Hole 0.001", "scores": {"class_score": 0.0011844635009765625}, "domain": "pixel"}, {"position": {"minX": 142.5, "minY": 291.75, "maxX": 154.75, "maxY": 326.75}, "class_id": 3, "box_caption": "FireExtinguisher 0.001", "scores": {"class_score": 0.0011491775512695312}, "domain": "pixel"}, {"position": {"minX": 67.5625, "minY": 215.0, "maxX": 80.9375, "maxY": 243.5}, "class_id": 7, "box_caption": "Valve 0.001", "scores": {"class_score": 0.001125335693359375}, "domain": "pixel"}, {"position": {"minX": 254.875, "minY": 242.25, "maxX": 278.25, "maxY": 292.25}, "class_id": 8, "box_caption": "Worning 0.001", "scores": {"class_score": 0.0011091232299804688}, "domain": "pixel"}, {"position": {"minX": 63.5, "minY": 211.75, "maxX": 88.625, "maxY": 267.25}, "class_id": 9, "box_caption": "people 0.001", "scores": {"class_score": 0.001079559326171875}, "domain": "pixel"}, {"position": {"minX": 250.875, "minY": 252.25, "maxX": 269.75, "maxY": 282.75}, "class_id": 7, "box_caption": "Valve 0.001", "scores": {"class_score": 0.0010671615600585938}, "domain": "pixel"}, {"position": {"minX": 63.5, "minY": 211.75, "maxX": 88.625, "maxY": 267.25}, "class_id": 12, "box_caption": "stairs 0.001", "scores": {"class_score": 0.0010585784912109375}, "domain": "pixel"}, {"position": {"minX": 67.5625, "minY": 215.0, "maxX": 80.9375, "maxY": 243.5}, "class_id": 6, "box_caption": "Tank 0.001", "scores": {"class_score": 0.0010423660278320312}, "domain": "pixel"}, {"position": {"minX": 69.9375, "minY": 217.125, "maxX": 80.8125, "maxY": 242.625}, "class_id": 1, "box_caption": "Cones 0.001", "scores": {"class_score": 0.001018524169921875}, "domain": "pixel"}, {"position": {"minX": 250.875, "minY": 252.25, "maxX": 269.75, "maxY": 282.75}, "class_id": 3, "box_caption": "FireExtinguisher 0.001", "scores": {"class_score": 0.001018524169921875}, "domain": "pixel"}, {"position": {"minX": 461.75, "minY": 335.0, "maxX": 600.0, "maxY": 379.5}, "class_id": 2, "box_caption": "ElectricBox 0.001", "scores": {"class_score": 0.001010894775390625}, "domain": "pixel"}, {"position": {"minX": 70.25, "minY": 216.5, "maxX": 80.75, "maxY": 243.5}, "class_id": 10, "box_caption": "people0 0.001", "scores": {"class_score": 0.0010061264038085938}, "domain": "pixel"}, {"position": {"minX": 69.25, "minY": 217.125, "maxX": 82.0, "maxY": 246.125}, "class_id": 11, "box_caption": "people1 0.001", "scores": {"class_score": 0.0010023117065429688}, "domain": "pixel"}, {"position": {"minX": 451.75, "minY": 295.25, "maxX": 468.25, "maxY": 334.75}, "class_id": 4, "box_caption": "Hole 0.001", "scores": {"class_score": 0.0010023117065429688}, "domain": "pixel"}], "class_labels": {"0": "Chemicals", "1": "Cones", "2": "ElectricBox", "3": "FireExtinguisher", "4": "Hole", "5": "Ladder", "6": "Tank", "7": "Valve", "8": "Worning", "9": "people", "10": "people0", "11": "people1", "12": "stairs"}}