{"box_data": [{"position": {"minX": 125.5, "minY": 193.625, "maxX": 145.5, "maxY": 226.375}, "class_id": 8, "box_caption": "Worning 0.612", "scores": {"class_score": 0.61181640625}, "domain": "pixel"}, {"position": {"minX": 106.0625, "minY": 129.25, "maxX": 210.5, "maxY": 362.25}, "class_id": 2, "box_caption": "ElectricBox 0.524", "scores": {"class_score": 0.5244140625}, "domain": "pixel"}, {"position": {"minX": 248.875, "minY": 323.75, "maxX": 283.0, "maxY": 417.75}, "class_id": 3, "box_caption": "FireExtinguisher 0.467", "scores": {"class_score": 0.466552734375}, "domain": "pixel"}, {"position": {"minX": 241.625, "minY": 333.75, "maxX": 290.0, "maxY": 405.75}, "class_id": 3, "box_caption": "FireExtinguisher 0.115", "scores": {"class_score": 0.11468505859375}, "domain": "pixel"}, {"position": {"minX": 120.9375, "minY": 185.0, "maxX": 146.625, "maxY": 234.0}, "class_id": 8, "box_caption": "Worning 0.084", "scores": {"class_score": 0.0836181640625}, "domain": "pixel"}, {"position": {"minX": 106.1875, "minY": 138.25, "maxX": 175.0, "maxY": 320.5}, "class_id": 2, "box_caption": "ElectricBox 0.049", "scores": {"class_score": 0.048553466796875}, "domain": "pixel"}, {"position": {"minX": 242.875, "minY": 326.0, "maxX": 278.5, "maxY": 396.5}, "class_id": 3, "box_caption": "FireExtinguisher 0.038", "scores": {"class_score": 0.038116455078125}, "domain": "pixel"}, {"position": {"minX": 35.875, "minY": 466.25, "maxX": 310.0, "maxY": 522.0}, "class_id": 2, "box_caption": "ElectricBox 0.029", "scores": {"class_score": 0.0290069580078125}, "domain": "pixel"}, {"position": {"minX": 135.375, "minY": 108.375, "maxX": 219.125, "maxY": 380.0}, "class_id": 2, "box_caption": "ElectricBox 0.025", "scores": {"class_score": 0.025421142578125}, "domain": "pixel"}, {"position": {"minX": 250.0, "minY": 349.0, "maxX": 277.5, "maxY": 399.0}, "class_id": 3, "box_caption": "FireExtinguisher 0.024", "scores": {"class_score": 0.023529052734375}, "domain": "pixel"}, {"position": {"minX": 120.25, "minY": 177.75, "maxX": 155.75, "maxY": 252.75}, "class_id": 8, "box_caption": "Worning 0.022", "scores": {"class_score": 0.0218658447265625}, "domain": "pixel"}, {"position": {"minX": 464.0, "minY": 135.375, "maxX": 694.0, "maxY": 518.0}, "class_id": 2, "box_caption": "ElectricBox 0.021", "scores": {"class_score": 0.020843505859375}, "domain": "pixel"}, {"position": {"minX": 3.296875, "minY": 489.5, "maxX": 42.0625, "maxY": 513.5}, "class_id": 2, "box_caption": "ElectricBox 0.019", "scores": {"class_score": 0.018707275390625}, "domain": "pixel"}, {"position": {"minX": -1.390625, "minY": 487.5, "maxX": 54.375, "maxY": 515.5}, "class_id": 2, "box_caption": "ElectricBox 0.018", "scores": {"class_score": 0.0183868408203125}, "domain": "pixel"}, {"position": {"minX": 99.125, "minY": 113.5, "maxX": 214.375, "maxY": 378.0}, "class_id": 8, "box_caption": "Worning 0.016", "scores": {"class_score": 0.0160980224609375}, "domain": "pixel"}, {"position": {"minX": 87.375, "minY": 124.9375, "maxX": 170.375, "maxY": 357.25}, "class_id": 2, "box_caption": "ElectricBox 0.016", "scores": {"class_score": 0.0160369873046875}, "domain": "pixel"}, {"position": {"minX": 2.125, "minY": 419.5, "maxX": 305.5, "maxY": 533.5}, "class_id": 2, "box_caption": "ElectricBox 0.013", "scores": {"class_score": 0.012542724609375}, "domain": "pixel"}, {"position": {"minX": 248.875, "minY": 323.75, "maxX": 283.0, "maxY": 417.75}, "class_id": 9, "box_caption": "people 0.011", "scores": {"class_score": 0.01088714599609375}, "domain": "pixel"}, {"position": {"minX": 106.1875, "minY": 138.25, "maxX": 175.0, "maxY": 320.5}, "class_id": 8, "box_caption": "Worning 0.010", "scores": {"class_score": 0.00995635986328125}, "domain": "pixel"}, {"position": {"minX": 246.5, "minY": 335.0, "maxX": 281.5, "maxY": 412.0}, "class_id": 11, "box_caption": "people1 0.010", "scores": {"class_score": 0.00963592529296875}, "domain": "pixel"}, {"position": {"minX": 240.0, "minY": 331.25, "maxX": 291.0, "maxY": 412.75}, "class_id": 0, "box_caption": "Chemicals 0.009", "scores": {"class_score": 0.0093536376953125}, "domain": "pixel"}, {"position": {"minX": 126.5625, "minY": 159.625, "maxX": 221.25, "maxY": 333.0}, "class_id": 2, "box_caption": "ElectricBox 0.009", "scores": {"class_score": 0.008697509765625}, "domain": "pixel"}, {"position": {"minX": 99.125, "minY": 113.5, "maxX": 214.375, "maxY": 378.0}, "class_id": 0, "box_caption": "Chemicals 0.009", "scores": {"class_score": 0.0085601806640625}, "domain": "pixel"}, {"position": {"minX": 638.0, "minY": 465.25, "maxX": 661.0, "maxY": 500.25}, "class_id": 8, "box_caption": "Worning 0.008", "scores": {"class_score": 0.0083465576171875}, "domain": "pixel"}, {"position": {"minX": 99.125, "minY": 113.5, "maxX": 214.375, "maxY": 378.0}, "class_id": 9, "box_caption": "people 0.008", "scores": {"class_score": 0.00786590576171875}, "domain": "pixel"}, {"position": {"minX": 235.5, "minY": 312.0, "maxX": 285.5, "maxY": 412.5}, "class_id": 3, "box_caption": "FireExtinguisher 0.007", "scores": {"class_score": 0.0070648193359375}, "domain": "pixel"}, {"position": {"minX": 101.625, "minY": 124.6875, "maxX": 213.375, "maxY": 371.5}, "class_id": 11, "box_caption": "people1 0.007", "scores": {"class_score": 0.0068206787109375}, "domain": "pixel"}, {"position": {"minX": -15.59375, "minY": 484.25, "maxX": 108.5, "maxY": 519.0}, "class_id": 2, "box_caption": "ElectricBox 0.007", "scores": {"class_score": 0.006587982177734375}, "domain": "pixel"}, {"position": {"minX": 99.125, "minY": 113.5, "maxX": 214.375, "maxY": 378.0}, "class_id": 12, "box_caption": "stairs 0.006", "scores": {"class_score": 0.00608062744140625}, "domain": "pixel"}, {"position": {"minX": 104.25, "minY": 129.75, "maxX": 211.5, "maxY": 366.0}, "class_id": 10, "box_caption": "people0 0.006", "scores": {"class_score": 0.006072998046875}, "domain": "pixel"}, {"position": {"minX": 101.625, "minY": 124.6875, "maxX": 213.375, "maxY": 371.5}, "class_id": 7, "box_caption": "Valve 0.006", "scores": {"class_score": 0.0060577392578125}, "domain": "pixel"}, {"position": {"minX": 640.5, "minY": 445.0, "maxX": 666.5, "maxY": 499.5}, "class_id": 8, "box_caption": "Worning 0.006", "scores": {"class_score": 0.005970001220703125}, "domain": "pixel"}, {"position": {"minX": 489.75, "minY": 43.0, "maxX": 679.5, "maxY": 435.75}, "class_id": 2, "box_caption": "ElectricBox 0.006", "scores": {"class_score": 0.00594329833984375}, "domain": "pixel"}, {"position": {"minX": 251.75, "minY": 333.5, "maxX": 282.75, "maxY": 412.0}, "class_id": 6, "box_caption": "Tank 0.006", "scores": {"class_score": 0.005863189697265625}, "domain": "pixel"}, {"position": {"minX": 35.875, "minY": 466.25, "maxX": 310.0, "maxY": 522.0}, "class_id": 4, "box_caption": "Hole 0.006", "scores": {"class_score": 0.005840301513671875}, "domain": "pixel"}, {"position": {"minX": 248.875, "minY": 323.75, "maxX": 283.0, "maxY": 417.75}, "class_id": 8, "box_caption": "Worning 0.006", "scores": {"class_score": 0.005626678466796875}, "domain": "pixel"}, {"position": {"minX": 251.75, "minY": 333.5, "maxX": 282.75, "maxY": 412.0}, "class_id": 12, "box_caption": "stairs 0.005", "scores": {"class_score": 0.005474090576171875}, "domain": "pixel"}, {"position": {"minX": 108.6875, "minY": 123.1875, "maxX": 208.0, "maxY": 371.25}, "class_id": 5, "box_caption": "Ladder 0.005", "scores": {"class_score": 0.005451202392578125}, "domain": "pixel"}, {"position": {"minX": 125.625, "minY": 192.25, "maxX": 144.625, "maxY": 226.75}, "class_id": 6, "box_caption": "Tank 0.005", "scores": {"class_score": 0.005359649658203125}, "domain": "pixel"}, {"position": {"minX": 125.625, "minY": 192.25, "maxX": 144.625, "maxY": 226.75}, "class_id": 4, "box_caption": "Hole 0.005", "scores": {"class_score": 0.005298614501953125}, "domain": "pixel"}, {"position": {"minX": 352.5, "minY": 452.0, "maxX": 629.0, "maxY": 515.5}, "class_id": 2, "box_caption": "ElectricBox 0.005", "scores": {"class_score": 0.005260467529296875}, "domain": "pixel"}, {"position": {"minX": 240.0, "minY": 331.25, "maxX": 291.0, "maxY": 412.75}, "class_id": 6, "box_caption": "Tank 0.005", "scores": {"class_score": 0.005046844482421875}, "domain": "pixel"}, {"position": {"minX": 104.25, "minY": 129.75, "maxX": 211.5, "maxY": 366.0}, "class_id": 6, "box_caption": "Tank 0.005", "scores": {"class_score": 0.004985809326171875}, "domain": "pixel"}, {"position": {"minX": 352.5, "minY": 452.0, "maxX": 629.0, "maxY": 515.5}, "class_id": 4, "box_caption": "Hole 0.005", "scores": {"class_score": 0.004962921142578125}, "domain": "pixel"}, {"position": {"minX": 240.0, "minY": 331.25, "maxX": 291.0, "maxY": 412.75}, "class_id": 7, "box_caption": "Valve 0.005", "scores": {"class_score": 0.00489044189453125}, "domain": "pixel"}, {"position": {"minX": 125.9375, "minY": 189.0, "maxX": 146.25, "maxY": 228.0}, "class_id": 2, "box_caption": "ElectricBox 0.005", "scores": {"class_score": 0.004878997802734375}, "domain": "pixel"}, {"position": {"minX": 93.125, "minY": 152.25, "maxX": 162.625, "maxY": 307.0}, "class_id": 2, "box_caption": "ElectricBox 0.005", "scores": {"class_score": 0.0047454833984375}, "domain": "pixel"}, {"position": {"minX": 35.875, "minY": 466.25, "maxX": 310.0, "maxY": 522.0}, "class_id": 8, "box_caption": "Worning 0.005", "scores": {"class_score": 0.004680633544921875}, "domain": "pixel"}, {"position": {"minX": 101.625, "minY": 124.6875, "maxX": 213.375, "maxY": 371.5}, "class_id": 3, "box_caption": "FireExtinguisher 0.005", "scores": {"class_score": 0.00466156005859375}, "domain": "pixel"}, {"position": {"minX": 125.5, "minY": 193.625, "maxX": 145.5, "maxY": 226.375}, "class_id": 0, "box_caption": "Chemicals 0.005", "scores": {"class_score": 0.004608154296875}, "domain": "pixel"}, {"position": {"minX": 101.625, "minY": 124.6875, "maxX": 213.375, "maxY": 371.5}, "class_id": 4, "box_caption": "Hole 0.004", "scores": {"class_score": 0.004467010498046875}, "domain": "pixel"}, {"position": {"minX": 477.0, "minY": 66.375, "maxX": 656.0, "maxY": 339.0}, "class_id": 2, "box_caption": "ElectricBox 0.004", "scores": {"class_score": 0.004451751708984375}, "domain": "pixel"}, {"position": {"minX": 251.75, "minY": 333.5, "maxX": 282.75, "maxY": 412.0}, "class_id": 0, "box_caption": "Chemicals 0.004", "scores": {"class_score": 0.004444122314453125}, "domain": "pixel"}, {"position": {"minX": 634.5, "minY": 462.75, "maxX": 669.5, "maxY": 501.25}, "class_id": 8, "box_caption": "Worning 0.004", "scores": {"class_score": 0.004444122314453125}, "domain": "pixel"}, {"position": {"minX": 471.5, "minY": 220.75, "maxX": 666.5, "maxY": 472.75}, "class_id": 2, "box_caption": "ElectricBox 0.004", "scores": {"class_score": 0.004428863525390625}, "domain": "pixel"}, {"position": {"minX": 396.75, "minY": 50.125, "maxX": 673.0, "maxY": 318.0}, "class_id": 2, "box_caption": "ElectricBox 0.004", "scores": {"class_score": 0.00434112548828125}, "domain": "pixel"}, {"position": {"minX": 248.875, "minY": 323.75, "maxX": 283.0, "maxY": 417.75}, "class_id": 5, "box_caption": "Ladder 0.004", "scores": {"class_score": 0.004337310791015625}, "domain": "pixel"}, {"position": {"minX": 123.4375, "minY": 190.375, "maxX": 147.25, "maxY": 228.875}, "class_id": 1, "box_caption": "Cones 0.004", "scores": {"class_score": 0.004268646240234375}, "domain": "pixel"}, {"position": {"minX": 238.0, "minY": 330.0, "maxX": 286.0, "maxY": 412.0}, "class_id": 1, "box_caption": "Cones 0.004", "scores": {"class_score": 0.004192352294921875}, "domain": "pixel"}, {"position": {"minX": 247.125, "minY": 337.0, "maxX": 274.75, "maxY": 386.0}, "class_id": 3, "box_caption": "FireExtinguisher 0.004", "scores": {"class_score": 0.00405120849609375}, "domain": "pixel"}, {"position": {"minX": 125.625, "minY": 192.25, "maxX": 144.625, "maxY": 226.75}, "class_id": 10, "box_caption": "people0 0.004", "scores": {"class_score": 0.0040435791015625}, "domain": "pixel"}, {"position": {"minX": 125.625, "minY": 192.25, "maxX": 144.625, "maxY": 226.75}, "class_id": 9, "box_caption": "people 0.004", "scores": {"class_score": 0.0040283203125}, "domain": "pixel"}, {"position": {"minX": -8.75, "minY": 478.75, "maxX": 203.75, "maxY": 519.5}, "class_id": 2, "box_caption": "ElectricBox 0.004", "scores": {"class_score": 0.00395965576171875}, "domain": "pixel"}, {"position": {"minX": 123.4375, "minY": 190.375, "maxX": 147.25, "maxY": 228.875}, "class_id": 5, "box_caption": "Ladder 0.004", "scores": {"class_score": 0.003917694091796875}, "domain": "pixel"}, {"position": {"minX": 122.1875, "minY": 190.5, "maxX": 139.5, "maxY": 230.0}, "class_id": 8, "box_caption": "Worning 0.004", "scores": {"class_score": 0.0037441253662109375}, "domain": "pixel"}, {"position": {"minX": 101.625, "minY": 124.6875, "maxX": 213.375, "maxY": 371.5}, "class_id": 1, "box_caption": "Cones 0.004", "scores": {"class_score": 0.003711700439453125}, "domain": "pixel"}, {"position": {"minX": 126.375, "minY": 194.5, "maxX": 145.875, "maxY": 225.75}, "class_id": 12, "box_caption": "stairs 0.004", "scores": {"class_score": 0.0036869049072265625}, "domain": "pixel"}, {"position": {"minX": 209.75, "minY": 0.359375, "maxX": 336.25, "maxY": 33.625}, "class_id": 2, "box_caption": "ElectricBox 0.004", "scores": {"class_score": 0.003673553466796875}, "domain": "pixel"}, {"position": {"minX": 238.0, "minY": 330.0, "maxX": 286.0, "maxY": 412.0}, "class_id": 10, "box_caption": "people0 0.004", "scores": {"class_score": 0.0036716461181640625}, "domain": "pixel"}, {"position": {"minX": 241.625, "minY": 333.75, "maxX": 290.0, "maxY": 405.75}, "class_id": 8, "box_caption": "Worning 0.004", "scores": {"class_score": 0.0036067962646484375}, "domain": "pixel"}, {"position": {"minX": 241.625, "minY": 333.75, "maxX": 290.0, "maxY": 405.75}, "class_id": 9, "box_caption": "people 0.004", "scores": {"class_score": 0.0036067962646484375}, "domain": "pixel"}, {"position": {"minX": 356.5, "minY": 5.625, "maxX": 705.5, "maxY": 404.0}, "class_id": 2, "box_caption": "ElectricBox 0.004", "scores": {"class_score": 0.003528594970703125}, "domain": "pixel"}, {"position": {"minX": 125.625, "minY": 192.25, "maxX": 144.625, "maxY": 226.75}, "class_id": 3, "box_caption": "FireExtinguisher 0.003", "scores": {"class_score": 0.0034236907958984375}, "domain": "pixel"}, {"position": {"minX": 352.5, "minY": 452.0, "maxX": 629.0, "maxY": 515.5}, "class_id": 8, "box_caption": "Worning 0.003", "scores": {"class_score": 0.00341796875}, "domain": "pixel"}, {"position": {"minX": 126.6875, "minY": 191.875, "maxX": 145.75, "maxY": 224.625}, "class_id": 7, "box_caption": "Valve 0.003", "scores": {"class_score": 0.0033588409423828125}, "domain": "pixel"}, {"position": {"minX": 519.5, "minY": 165.625, "maxX": 699.5, "maxY": 463.0}, "class_id": 2, "box_caption": "ElectricBox 0.003", "scores": {"class_score": 0.003322601318359375}, "domain": "pixel"}, {"position": {"minX": 99.8125, "minY": 150.75, "maxX": 130.5, "maxY": 193.0}, "class_id": 2, "box_caption": "ElectricBox 0.003", "scores": {"class_score": 0.0031185150146484375}, "domain": "pixel"}, {"position": {"minX": 551.5, "minY": 473.5, "maxX": 671.5, "maxY": 511.0}, "class_id": 2, "box_caption": "ElectricBox 0.003", "scores": {"class_score": 0.0030956268310546875}, "domain": "pixel"}, {"position": {"minX": 176.375, "minY": 346.0, "maxX": 233.125, "maxY": 383.5}, "class_id": 8, "box_caption": "Worning 0.003", "scores": {"class_score": 0.0030193328857421875}, "domain": "pixel"}, {"position": {"minX": 120.875, "minY": 484.25, "maxX": 312.0, "maxY": 513.5}, "class_id": 2, "box_caption": "ElectricBox 0.003", "scores": {"class_score": 0.002838134765625}, "domain": "pixel"}, {"position": {"minX": 125.5, "minY": 193.625, "maxX": 145.5, "maxY": 226.375}, "class_id": 11, "box_caption": "people1 0.003", "scores": {"class_score": 0.0027828216552734375}, "domain": "pixel"}, {"position": {"minX": 132.125, "minY": 188.625, "maxX": 149.125, "maxY": 228.375}, "class_id": 8, "box_caption": "Worning 0.003", "scores": {"class_score": 0.0027256011962890625}, "domain": "pixel"}, {"position": {"minX": 424.5, "minY": 468.75, "maxX": 661.5, "maxY": 514.5}, "class_id": 2, "box_caption": "ElectricBox 0.003", "scores": {"class_score": 0.002712249755859375}, "domain": "pixel"}, {"position": {"minX": 349.25, "minY": 142.75, "maxX": 724.0, "maxY": 543.0}, "class_id": 2, "box_caption": "ElectricBox 0.003", "scores": {"class_score": 0.0027103424072265625}, "domain": "pixel"}, {"position": {"minX": 248.875, "minY": 323.75, "maxX": 283.0, "maxY": 417.75}, "class_id": 2, "box_caption": "ElectricBox 0.003", "scores": {"class_score": 0.002552032470703125}, "domain": "pixel"}, {"position": {"minX": 241.5, "minY": 326.5, "maxX": 280.5, "maxY": 396.0}, "class_id": 0, "box_caption": "Chemicals 0.003", "scores": {"class_score": 0.0025424957275390625}, "domain": "pixel"}, {"position": {"minX": 248.875, "minY": 323.75, "maxX": 283.0, "maxY": 417.75}, "class_id": 4, "box_caption": "Hole 0.003", "scores": {"class_score": 0.002521514892578125}, "domain": "pixel"}, {"position": {"minX": 251.75, "minY": 333.5, "maxX": 282.75, "maxY": 412.0}, "class_id": 7, "box_caption": "Valve 0.002", "scores": {"class_score": 0.00246429443359375}, "domain": "pixel"}, {"position": {"minX": 240.0, "minY": 331.25, "maxX": 291.0, "maxY": 412.75}, "class_id": 12, "box_caption": "stairs 0.002", "scores": {"class_score": 0.0024433135986328125}, "domain": "pixel"}, {"position": {"minX": 223.875, "minY": 449.75, "maxX": 296.0, "maxY": 487.25}, "class_id": 8, "box_caption": "Worning 0.002", "scores": {"class_score": 0.002429962158203125}, "domain": "pixel"}, {"position": {"minX": -3.75, "minY": 487.75, "maxX": 160.0, "maxY": 517.5}, "class_id": 2, "box_caption": "ElectricBox 0.002", "scores": {"class_score": 0.00240325927734375}, "domain": "pixel"}, {"position": {"minX": 120.25, "minY": 177.75, "maxX": 155.75, "maxY": 252.75}, "class_id": 2, "box_caption": "ElectricBox 0.002", "scores": {"class_score": 0.0022983551025390625}, "domain": "pixel"}, {"position": {"minX": 117.4375, "minY": 466.5, "maxX": 322.0, "maxY": 515.0}, "class_id": 4, "box_caption": "Hole 0.002", "scores": {"class_score": 0.0022678375244140625}, "domain": "pixel"}, {"position": {"minX": 190.0, "minY": 0.109375, "maxX": 302.0, "maxY": 39.9375}, "class_id": 2, "box_caption": "ElectricBox 0.002", "scores": {"class_score": 0.002231597900390625}, "domain": "pixel"}, {"position": {"minX": -2.703125, "minY": 496.0, "maxX": 49.4375, "maxY": 514.0}, "class_id": 2, "box_caption": "ElectricBox 0.002", "scores": {"class_score": 0.0021877288818359375}, "domain": "pixel"}, {"position": {"minX": 239.125, "minY": 1.03125, "maxX": 363.5, "maxY": 30.71875}, "class_id": 2, "box_caption": "ElectricBox 0.002", "scores": {"class_score": 0.0021419525146484375}, "domain": "pixel"}, {"position": {"minX": 183.25, "minY": -1.0, "maxX": 222.25, "maxY": 51.0}, "class_id": 8, "box_caption": "Worning 0.002", "scores": {"class_score": 0.0020751953125}, "domain": "pixel"}, {"position": {"minX": -1.515625, "minY": 482.25, "maxX": 38.0625, "maxY": 518.5}, "class_id": 2, "box_caption": "ElectricBox 0.002", "scores": {"class_score": 0.0020599365234375}, "domain": "pixel"}, {"position": {"minX": 193.0, "minY": 6.484375, "maxX": 216.5, "maxY": 50.6875}, "class_id": 8, "box_caption": "Worning 0.002", "scores": {"class_score": 0.0017948150634765625}, "domain": "pixel"}, {"position": {"minX": 241.625, "minY": 333.75, "maxX": 290.0, "maxY": 405.75}, "class_id": 5, "box_caption": "Ladder 0.002", "scores": {"class_score": 0.00179290771484375}, "domain": "pixel"}, {"position": {"minX": 649.0, "minY": 444.5, "maxX": 669.0, "maxY": 502.5}, "class_id": 8, "box_caption": "Worning 0.002", "scores": {"class_score": 0.0016393661499023438}, "domain": "pixel"}, {"position": {"minX": 479.0, "minY": 133.25, "maxX": 660.0, "maxY": 400.75}, "class_id": 2, "box_caption": "ElectricBox 0.002", "scores": {"class_score": 0.0016384124755859375}, "domain": "pixel"}, {"position": {"minX": 35.875, "minY": 466.25, "maxX": 310.0, "maxY": 522.0}, "class_id": 12, "box_caption": "stairs 0.002", "scores": {"class_score": 0.0016326904296875}, "domain": "pixel"}, {"position": {"minX": 517.5, "minY": 466.0, "maxX": 674.5, "maxY": 514.0}, "class_id": 2, "box_caption": "ElectricBox 0.002", "scores": {"class_score": 0.0016193389892578125}, "domain": "pixel"}, {"position": {"minX": 80.25, "minY": 158.0, "maxX": 136.25, "maxY": 321.25}, "class_id": 2, "box_caption": "ElectricBox 0.002", "scores": {"class_score": 0.001583099365234375}, "domain": "pixel"}, {"position": {"minX": 163.0, "minY": 350.25, "maxX": 227.75, "maxY": 378.25}, "class_id": 8, "box_caption": "Worning 0.002", "scores": {"class_score": 0.0015668869018554688}, "domain": "pixel"}, {"position": {"minX": 123.375, "minY": 188.125, "maxX": 148.375, "maxY": 229.125}, "class_id": 12, "box_caption": "stairs 0.002", "scores": {"class_score": 0.0015497207641601562}, "domain": "pixel"}, {"position": {"minX": 577.0, "minY": 453.25, "maxX": 685.0, "maxY": 509.25}, "class_id": 2, "box_caption": "ElectricBox 0.002", "scores": {"class_score": 0.0015192031860351562}, "domain": "pixel"}, {"position": {"minX": 241.625, "minY": 333.75, "maxX": 290.0, "maxY": 405.75}, "class_id": 4, "box_caption": "Hole 0.002", "scores": {"class_score": 0.001506805419921875}, "domain": "pixel"}, {"position": {"minX": 113.0625, "minY": 459.25, "maxX": 319.25, "maxY": 527.5}, "class_id": 2, "box_caption": "ElectricBox 0.001", "scores": {"class_score": 0.0014944076538085938}, "domain": "pixel"}, {"position": {"minX": 104.6875, "minY": 158.75, "maxX": 222.5, "maxY": 330.5}, "class_id": 8, "box_caption": "Worning 0.001", "scores": {"class_score": 0.0014524459838867188}, "domain": "pixel"}, {"position": {"minX": 146.0, "minY": 348.5, "maxX": 230.25, "maxY": 381.5}, "class_id": 2, "box_caption": "ElectricBox 0.001", "scores": {"class_score": 0.0014476776123046875}, "domain": "pixel"}, {"position": {"minX": 336.25, "minY": 0.53125, "maxX": 472.25, "maxY": 35.34375}, "class_id": 2, "box_caption": "ElectricBox 0.001", "scores": {"class_score": 0.0014276504516601562}, "domain": "pixel"}, {"position": {"minX": 96.0, "minY": 183.75, "maxX": 107.0, "maxY": 222.75}, "class_id": 8, "box_caption": "Worning 0.001", "scores": {"class_score": 0.0014104843139648438}, "domain": "pixel"}, {"position": {"minX": 217.25, "minY": 435.25, "maxX": 306.75, "maxY": 489.25}, "class_id": 8, "box_caption": "Worning 0.001", "scores": {"class_score": 0.001392364501953125}, "domain": "pixel"}, {"position": {"minX": 117.4375, "minY": 466.5, "maxX": 322.0, "maxY": 515.0}, "class_id": 8, "box_caption": "Worning 0.001", "scores": {"class_score": 0.001392364501953125}, "domain": "pixel"}, {"position": {"minX": 181.625, "minY": 4.65625, "maxX": 249.375, "maxY": 42.59375}, "class_id": 8, "box_caption": "Worning 0.001", "scores": {"class_score": 0.00138092041015625}, "domain": "pixel"}, {"position": {"minX": 279.5, "minY": 427.5, "maxX": 602.0, "maxY": 516.0}, "class_id": 4, "box_caption": "Hole 0.001", "scores": {"class_score": 0.0013713836669921875}, "domain": "pixel"}, {"position": {"minX": 279.5, "minY": 427.5, "maxX": 602.0, "maxY": 516.0}, "class_id": 2, "box_caption": "ElectricBox 0.001", "scores": {"class_score": 0.0013666152954101562}, "domain": "pixel"}, {"position": {"minX": 31.25, "minY": 485.5, "maxX": 223.0, "maxY": 515.5}, "class_id": 2, "box_caption": "ElectricBox 0.001", "scores": {"class_score": 0.00136566162109375}, "domain": "pixel"}, {"position": {"minX": 209.125, "minY": 10.765625, "maxX": 270.25, "maxY": 50.625}, "class_id": 2, "box_caption": "ElectricBox 0.001", "scores": {"class_score": 0.0013608932495117188}, "domain": "pixel"}, {"position": {"minX": 241.5, "minY": 326.5, "maxX": 280.5, "maxY": 396.0}, "class_id": 12, "box_caption": "stairs 0.001", "scores": {"class_score": 0.0013246536254882812}, "domain": "pixel"}, {"position": {"minX": 35.875, "minY": 466.25, "maxX": 310.0, "maxY": 522.0}, "class_id": 0, "box_caption": "Chemicals 0.001", "scores": {"class_score": 0.001293182373046875}, "domain": "pixel"}, {"position": {"minX": 110.125, "minY": 165.75, "maxX": 161.875, "maxY": 284.75}, "class_id": 8, "box_caption": "Worning 0.001", "scores": {"class_score": 0.00128936767578125}, "domain": "pixel"}, {"position": {"minX": 35.875, "minY": 466.25, "maxX": 310.0, "maxY": 522.0}, "class_id": 11, "box_caption": "people1 0.001", "scores": {"class_score": 0.0012788772583007812}, "domain": "pixel"}, {"position": {"minX": 352.5, "minY": 452.0, "maxX": 629.0, "maxY": 515.5}, "class_id": 12, "box_caption": "stairs 0.001", "scores": {"class_score": 0.0012378692626953125}, "domain": "pixel"}, {"position": {"minX": 646.5, "minY": 460.75, "maxX": 670.5, "maxY": 512.0}, "class_id": 8, "box_caption": "Worning 0.001", "scores": {"class_score": 0.0012302398681640625}, "domain": "pixel"}, {"position": {"minX": 237.0, "minY": 328.25, "maxX": 279.0, "maxY": 401.25}, "class_id": 2, "box_caption": "ElectricBox 0.001", "scores": {"class_score": 0.0012006759643554688}, "domain": "pixel"}, {"position": {"minX": 343.0, "minY": 29.875, "maxX": 615.0, "maxY": 349.0}, "class_id": 2, "box_caption": "ElectricBox 0.001", "scores": {"class_score": 0.001163482666015625}, "domain": "pixel"}, {"position": {"minX": 374.25, "minY": 223.0, "maxX": 639.0, "maxY": 475.0}, "class_id": 2, "box_caption": "ElectricBox 0.001", "scores": {"class_score": 0.0011501312255859375}, "domain": "pixel"}, {"position": {"minX": 97.1875, "minY": 154.5, "maxX": 121.8125, "maxY": 192.0}, "class_id": 2, "box_caption": "ElectricBox 0.001", "scores": {"class_score": 0.0011358261108398438}, "domain": "pixel"}, {"position": {"minX": 109.0625, "minY": 147.0, "maxX": 141.25, "maxY": 185.75}, "class_id": 2, "box_caption": "ElectricBox 0.001", "scores": {"class_score": 0.0011348724365234375}, "domain": "pixel"}, {"position": {"minX": -4.046875, "minY": 482.25, "maxX": 24.796875, "maxY": 511.75}, "class_id": 2, "box_caption": "ElectricBox 0.001", "scores": {"class_score": 0.0011348724365234375}, "domain": "pixel"}, {"position": {"minX": 430.25, "minY": 62.625, "maxX": 610.0, "maxY": 339.0}, "class_id": 2, "box_caption": "ElectricBox 0.001", "scores": {"class_score": 0.0010824203491210938}, "domain": "pixel"}, {"position": {"minX": 84.25, "minY": 138.5, "maxX": 229.75, "maxY": 402.5}, "class_id": 2, "box_caption": "ElectricBox 0.001", "scores": {"class_score": 0.0010824203491210938}, "domain": "pixel"}, {"position": {"minX": 198.25, "minY": 454.25, "maxX": 321.25, "maxY": 498.75}, "class_id": 8, "box_caption": "Worning 0.001", "scores": {"class_score": 0.0010623931884765625}, "domain": "pixel"}, {"position": {"minX": 254.375, "minY": 459.5, "maxX": 557.5, "maxY": 520.0}, "class_id": 2, "box_caption": "ElectricBox 0.001", "scores": {"class_score": 0.0010480880737304688}, "domain": "pixel"}, {"position": {"minX": 21.8125, "minY": 380.0, "maxX": 276.5, "maxY": 518.5}, "class_id": 2, "box_caption": "ElectricBox 0.001", "scores": {"class_score": 0.0010356903076171875}, "domain": "pixel"}, {"position": {"minX": 181.625, "minY": 4.65625, "maxX": 249.375, "maxY": 42.59375}, "class_id": 2, "box_caption": "ElectricBox 0.001", "scores": {"class_score": 0.0010099411010742188}, "domain": "pixel"}], "class_labels": {"0": "Chemicals", "1": "Cones", "2": "ElectricBox", "3": "FireExtinguisher", "4": "Hole", "5": "Ladder", "6": "Tank", "7": "Valve", "8": "Worning", "9": "people", "10": "people0", "11": "people1", "12": "stairs"}}